{
    "totalCount": 119,
    "youtubeCount": {
        "total": 64,
        "totalLinks": 45,
        "totalLinksAvailable": 14
    },
    "patreonCount": {
        "total": 55,
        "totalLinks": 39,
        "totalLinksAvailable": 39
    },
    "youtube": [
        {
            "source": "youtube",
            "title": "February 12th 1993 The Case of James Bulger",
            "releaseDate": "",
            "links": {},
            "aliases": [],
            "runtime": "00:18:52"
        },
        {
            "source": "youtube",
            "title": "Life After Prison",
            "releaseDate": "2018-10-01",
            "links": [
                {
                    "link": "https://www.youtube.com/watch?v=lJpZxkQ_dso",
                    "availability": "Unavailable",
                    "runtime": "00:00:00"
                }
            ],
            "aliases": [],
            "runtime": "00:00:00"
        },
        {
            "source": "youtube",
            "title": "Young Prisoners - Vehicular Manslaughter",
            "releaseDate": "2018-10-02",
            "links": [
                {
                    "link": "https://www.youtube.com/watch?v=BlqFUmRamN4",
                    "availability": "Unavailable",
                    "runtime": "00:00:00"
                }
            ],
            "aliases": [],
            "runtime": "00:00:00"
        },
        {
            "source": "youtube",
            "title": "Young Prisoners - First Degree Murder",
            "releaseDate": "2018-10-02",
            "links": [
                {
                    "link": "https://www.youtube.com/watch?v=55iy85X15Cc",
                    "availability": "Unavailable",
                    "runtime": "00:00:00"
                }
            ],
            "aliases": [],
            "runtime": "00:00:00"
        },
        {
            "source": "youtube",
            "title": "Life In Juvie - High-Max",
            "releaseDate": "2018-10-04",
            "links": [
                {
                    "link": "https://www.youtube.com/watch?v=yRb4NrKtXq4",
                    "availability": "Unavailable",
                    "runtime": "00:00:00"
                }
            ],
            "aliases": [],
            "runtime": "00:00:00"
        },
        {
            "source": "youtube",
            "title": "The Most Disturbing Police Interrogations pt. 3",
            "releaseDate": "2018-10-07",
            "links": [
                {
                    "link": "https://www.youtube.com/watch?v=26VQw4q9ZFU",
                    "availability": "Unavailable",
                    "runtime": "00:35:59"
                }
            ],
            "aliases": [],
            "runtime": "00:35:59"
        },
        {
            "source": "youtube",
            "title": "The Most Compelling Police Interrogations pt. 4",
            "releaseDate": "2018-10-14",
            "links": [
                {
                    "link": "https://www.youtube.com/watch?v=DcqLYjBwcrk ",
                    "availability": "Unavailable",
                    "runtime": "00:32:51"
                }
            ],
            "aliases": [],
            "runtime": "00:32:51"
        },
        {
            "source": "youtube",
            "title": "The Most Compelling Prison Interviews",
            "releaseDate": "2018-10-15",
            "links": [
                {
                    "link": "https://www.youtube.com/watch?v=poOgEoN9J0E",
                    "availability": "Unavailable",
                    "runtime": "00:00:00"
                }
            ],
            "aliases": [],
            "runtime": "00:00:00"
        },
        {
            "source": "youtube",
            "title": "The Interrogation of Jodi Arias",
            "releaseDate": "2018-10-18",
            "links": {},
            "aliases": [],
            "runtime": "02:10:44"
        },
        {
            "source": "youtube",
            "title": "The Most Compelling Police Interrogations",
            "releaseDate": "2018-10-24",
            "links": [
                {
                    "link": "https://www.youtube.com/watch?v=d8mByf4CRis",
                    "availability": "Unavailable",
                    "runtime": "00:19:49"
                }
            ],
            "aliases": [],
            "runtime": "00:19:49"
        },
        {
            "source": "youtube",
            "title": "The Most Compelling Police Interrogations pt. 2",
            "releaseDate": "2018-10-30",
            "links": {},
            "aliases": [],
            "runtime": "00:49:45"
        },
        {
            "source": "youtube",
            "title": "The Most Compelling Police Interrogations pt. 3",
            "releaseDate": "2018-11-01",
            "links": [
                {
                    "link": "https://www.youtube.com/watch?v=D7-3CA_BaAw",
                    "availability": "Unavailable",
                    "runtime": "00:35:59"
                }
            ],
            "aliases": [],
            "runtime": "00:35:59"
        },
        {
            "source": "youtube",
            "title": "The Most Compelling Police Interrogations pt. 4",
            "releaseDate": "2018-11-12",
            "links": [
                {
                    "link": "https://www.youtube.com/watch?v=_WnhP91NJeU",
                    "availability": "Unavailable",
                    "runtime": "00:42:58"
                }
            ],
            "aliases": [],
            "runtime": "00:42:58"
        },
        {
            "source": "youtube",
            "title": "The Most Compelling Police Interrogations pt. 5",
            "releaseDate": "2018-11-25",
            "links": [
                {
                    "link": "https://www.youtube.com/watch?v=3JbjrGT84xk",
                    "availability": "Unavailable",
                    "runtime": "00:49:45"
                }
            ],
            "aliases": [],
            "runtime": "00:49:45"
        },
        {
            "source": "youtube",
            "title": "The Most Compelling Police Interrogations pt. 6",
            "releaseDate": "2018-11-25",
            "links": [
                {
                    "link": "https://www.youtube.com/watch?v=5izGovLYoF0",
                    "availability": "Unavailable",
                    "runtime": "00:29:28"
                }
            ],
            "aliases": [],
            "runtime": "00:29:28"
        },
        {
            "source": "youtube",
            "title": "The Most Compelling Police Interrogations pt. 7",
            "releaseDate": "2018-12-05",
            "links": {},
            "aliases": [],
            "runtime": "01:03:24"
        },
        {
            "source": "youtube",
            "title": "The Truth About Narcissism",
            "releaseDate": "2018-12-27",
            "links": [
                {
                    "link": "https://www.youtube.com/watch?v=wM5e-8WwgyE",
                    "availability": "Unavailable",
                    "runtime": "00:07:10"
                }
            ],
            "aliases": [],
            "runtime": "00:07:10"
        },
        {
            "source": "youtube",
            "title": "The Most Compelling Police Interrogations pt. 8 - 1",
            "releaseDate": "2019-01-01",
            "links": [
                {
                    "link": "https://www.youtube.com/watch?v=MYK_eVpRyqc",
                    "availability": "Unavailable",
                    "runtime": "00:37:02"
                }
            ],
            "aliases": [],
            "runtime": "00:37:02"
        },
        {
            "source": "youtube",
            "title": "The Lifer Perspective pt. 1",
            "releaseDate": "2019-01-13",
            "links": [
                {
                    "link": "https://www.youtube.com/watch?v=9LqZFAYOjGw",
                    "availability": "Unavailable",
                    "runtime": "00:10:11"
                }
            ],
            "aliases": [],
            "runtime": "00:10:11"
        },
        {
            "source": "youtube",
            "title": "The Case of Chris Watts - pt. 1",
            "releaseDate": "2019-01-17",
            "links": {},
            "aliases": [],
            "runtime": "00:21:19"
        },
        {
            "source": "youtube",
            "title": "The Case of Chris Watts - Part 2 - The Polygraph",
            "releaseDate": "2019-01-23",
            "links": {},
            "aliases": [],
            "runtime": "00:24:24"
        },
        {
            "source": "youtube",
            "title": "The Case of Chris Watts - Part 3 - The Confession",
            "releaseDate": "2019-01-29",
            "links": {},
            "aliases": [],
            "runtime": "00:30:37"
        },
        {
            "source": "youtube",
            "title": "The Case of Chris Watts pt.4 - Nichol Kessinger",
            "releaseDate": "2019-02-26",
            "links": [
                {
                    "link": "https://www.youtube.com/watch?v=2AWmgbaf97I",
                    "availability": "Unavailable",
                    "runtime": "00:48:33"
                }
            ],
            "aliases": [],
            "runtime": "00:48:33"
        },
        {
            "source": "youtube",
            "title": "Shaun Attwood's Interrogations",
            "releaseDate": "2019-02-28",
            "links": [
                {
                    "link": "https://www.youtube.com/watch?v=r8JHC3lUMis",
                    "availability": "Unavailable",
                    "runtime": "00:21:44"
                }
            ],
            "aliases": [],
            "runtime": "00:21:44"
        },
        {
            "source": "youtube",
            "title": "Christina's Prison Story",
            "releaseDate": "2019-02-28",
            "links": [
                {
                    "link": "https://www.youtube.com/watch?v=6RqPFZsXSu0",
                    "availability": "Unavailable",
                    "runtime": "00:12:08"
                }
            ],
            "aliases": [],
            "runtime": "00:12:08"
        },
        {
            "source": "youtube",
            "title": "The Insanity Defense pt. 1",
            "releaseDate": "2019-03-03",
            "links": [
                {
                    "link": "https://www.youtube.com/watch?v=tfZJ0_pGCRs",
                    "availability": "Unavailable",
                    "runtime": "00:25:23"
                }
            ],
            "aliases": [],
            "runtime": "00:25:23"
        },
        {
            "source": "youtube",
            "title": "The Interrogation of Steven J. Williams",
            "releaseDate": "2019-03-15",
            "links": [
                {
                    "link": "https://www.youtube.com/watch?v=ERY1v3fYr_A",
                    "availability": "Unavailable",
                    "runtime": "00:42:12"
                }
            ],
            "aliases": [],
            "runtime": "00:42:12"
        },
        {
            "source": "youtube",
            "title": "The Interrogations of Amber Hilberling & Cameron Rogers",
            "releaseDate": "2019-03-30",
            "links": [
                {
                    "link": "https://www.youtube.com/watch?v=QSQUxqlAjHg",
                    "availability": "Unavailable",
                    "runtime": "00:52:57"
                }
            ],
            "aliases": [],
            "runtime": "00:52:57"
        },
        {
            "source": "youtube",
            "title": "The Most Compelling Police Interrogations pt. 7",
            "releaseDate": "2019-03-31",
            "links": [
                {
                    "link": "https://www.youtube.com/watch?v=hneR5LqrNw4",
                    "availability": "Unavailable",
                    "runtime": "01:01:54"
                }
            ],
            "aliases": [],
            "runtime": "01:01:54"
        },
        {
            "source": "youtube",
            "title": "The Case of Jussie Smollett",
            "releaseDate": "2019-04-09",
            "links": {},
            "aliases": [],
            "runtime": "00:38:36"
        },
        {
            "source": "youtube",
            "title": "The Most Compelling Police Interrogations pt. 8 - 2",
            "releaseDate": "2019-05-01",
            "links": [
                {
                    "link": "https://www.youtube.com/watch?v=5fmhLRkeruM",
                    "availability": "Unavailable",
                    "runtime": "00:52:18"
                }
            ],
            "aliases": [],
            "runtime": "00:52:18"
        },
        {
            "source": "youtube",
            "title": "The Death Row Phenomenon",
            "releaseDate": "2019-05-21",
            "links": [
                {
                    "link": "https://www.youtube.com/watch?v=rGU16w3gGbs",
                    "availability": "Unavailable",
                    "runtime": "00:49:25"
                }
            ],
            "aliases": [],
            "runtime": "00:49:25"
        },
        {
            "source": "youtube",
            "title": "The Interrogation of Christopher Garnier",
            "releaseDate": "2019-05-31",
            "links": [
                {
                    "link": "https://www.youtube.com/watch?v=KFAwQ-lhSOA",
                    "availability": "Unavailable",
                    "runtime": "00:34:01"
                }
            ],
            "aliases": [],
            "runtime": "00:34:01"
        },
        {
            "source": "youtube",
            "title": "The Psychology of Ted Bundy",
            "releaseDate": "2019-06-19",
            "links": [
                {
                    "link": "https://www.youtube.com/watch?v=6FGmHyMNQdM",
                    "availability": "Unavailable",
                    "runtime": "00:51:45"
                }
            ],
            "aliases": [],
            "runtime": "00:51:45"
        },
        {
            "source": "youtube",
            "title": "The Interrogations of Mr. Mathews and Miss Hoare",
            "releaseDate": "2019-07-03",
            "links": [
                {
                    "link": "https://www.youtube.com/watch?v=84TT89V7_Yo",
                    "availability": "Unavailable",
                    "runtime": "00:57:52"
                }
            ],
            "aliases": [],
            "runtime": "00:57:52"
        },
        {
            "source": "youtube",
            "title": "The Interrogation of Col. Russell Williams",
            "releaseDate": "2019-08-03",
            "links": [
                {
                    "link": "https://www.youtube.com/watch?v=jJZv3z7FOt0",
                    "availability": "Available",
                    "runtime": "01:07:54"
                }
            ],
            "aliases": [],
            "runtime": "01:06:33"
        },
        {
            "source": "youtube",
            "title": "The Psychology of Brooke Houts",
            "releaseDate": "2019-08-08",
            "links": [
                {
                    "link": "https://www.youtube.com/watch?v=V26p0vg_GLQ",
                    "availability": "Unavailable",
                    "runtime": "00:06:36"
                }
            ],
            "aliases": [],
            "runtime": "00:06:36"
        },
        {
            "source": "youtube",
            "title": "The Interrogation of Stephanie Lazarus",
            "releaseDate": "2019-08-21",
            "links": {},
            "aliases": [],
            "runtime": "00:50:18"
        },
        {
            "source": "youtube",
            "title": "The Case of Grant Amato",
            "releaseDate": "2019-08-31",
            "links": {},
            "aliases": [],
            "runtime": "01:41:40"
        },
        {
            "source": "youtube",
            "title": "The Interrogation of George the 5th",
            "releaseDate": "2019-09-25",
            "links": [
                {
                    "link": "https://www.youtube.com/watch?v=H1E39N-vmXE",
                    "availability": "Unavailable",
                    "runtime": "00:53:07"
                }
            ],
            "aliases": [],
            "runtime": "00:53:07"
        },
        {
            "source": "youtube",
            "title": "The Case of Phoenix Sinclair",
            "releaseDate": "2019-10-02",
            "links": [
                {
                    "link": "https://www.youtube.com/watch?v=w9SBNkZ3qoM",
                    "availability": "Unavailable",
                    "runtime": "00:40:02"
                }
            ],
            "aliases": [
                "Police Interrogations Part 17 - The Case of Phoenix Sinclair"
            ],
            "runtime": "00:40:02"
        },
        {
            "source": "youtube",
            "title": "The Case of Michael Drejka",
            "releaseDate": "2019-10-08",
            "links": {},
            "aliases": [],
            "runtime": "00:52:29"
        },
        {
            "source": "youtube",
            "title": "The Psychology of an Incel / The Case of Alek Minassian",
            "releaseDate": "2019-10-18",
            "links": [
                {
                    "link": "https://www.youtube.com/watch?v=cWgc_4WyYew",
                    "availability": "Unavailable",
                    "runtime": "00:55:01"
                }
            ],
            "aliases": [],
            "runtime": "00:55:01"
        },
        {
            "source": "youtube",
            "title": "The Case of Michael Rafferty",
            "releaseDate": "2019-11-06",
            "links": {},
            "aliases": [],
            "runtime": "00:57:28"
        },
        {
            "source": "youtube",
            "title": "The Psychology of Prince Andrew (Prince Andrew is not good at lying)",
            "releaseDate": "2019-11-25",
            "links": [
                {
                    "link": "https://www.youtube.com/watch?v=q-y2g9Ot5GA",
                    "availability": "Available",
                    "runtime": "00:06:07"
                }
            ],
            "aliases": [],
            "runtime": "00:06:07"
        },
        {
            "source": "youtube",
            "title": "The Psychology of Prince Andrew",
            "releaseDate": "2019-11-25",
            "links": {},
            "aliases": [],
            "runtime": "00:29:53"
        },
        {
            "source": "youtube",
            "title": "The Curious Case of Dalia Dippolito",
            "releaseDate": "2019-12-14",
            "links": [
                {
                    "link": "https://www.youtube.com/watch?v=7JttwV6XZ_I",
                    "availability": "Available",
                    "runtime": "00:50:28"
                }
            ],
            "aliases": [],
            "runtime": "00:50:27"
        },
        {
            "source": "youtube",
            "title": "Narcissistic Personality Disorder",
            "releaseDate": "2020-01-31",
            "links": [
                {
                    "link": "https://www.youtube.com/watch?v=khssrZ3Pb2M",
                    "availability": "Available",
                    "runtime": "00:07:09"
                }
            ],
            "aliases": [],
            "runtime": "00:07:09"
        },
        {
            "source": "youtube",
            "title": "The Case of Lee Rodarte",
            "releaseDate": "2020-02-11",
            "links": [
                {
                    "link": "https://www.youtube.com/watch?v=L0H6xYwMQnk",
                    "availability": "Available",
                    "runtime": "00:39:48"
                }
            ],
            "aliases": [],
            "runtime": "00:39:47"
        },
        {
            "source": "youtube",
            "title": "The Case of Michael Dunn",
            "releaseDate": "2020-02-20",
            "links": {},
            "aliases": [],
            "runtime": "00:57:35"
        },
        {
            "source": "youtube",
            "title": "The Case of Ms. Sorella",
            "releaseDate": "2020-03-05",
            "links": {},
            "aliases": [],
            "runtime": "00:17:00"
        },
        {
            "source": "youtube",
            "title": "The Case of Jon Koppenhaver",
            "releaseDate": "2020-04-17",
            "links": {},
            "aliases": [
                "The Case of Jon Koppenhaver (War Machine)"
            ],
            "runtime": "01:03:40"
        },
        {
            "source": "youtube",
            "title": "Interrogation of Mr. M",
            "releaseDate": "2020-04-30",
            "links": {},
            "aliases": [],
            "runtime": "00:24:41"
        },
        {
            "source": "youtube",
            "title": "The Case of Andy. B",
            "releaseDate": "2020-06-02",
            "links": {},
            "aliases": [],
            "runtime": "00:25:09"
        },
        {
            "source": "youtube",
            "title": "The Bizarre Case of Stephen McDaniel",
            "releaseDate": "2020-06-16",
            "links": [
                {
                    "link": "https://www.youtube.com/watch?v=HkRjIq8Cp2A",
                    "availability": "Available",
                    "runtime": "00:42:12"
                }
            ],
            "aliases": [],
            "runtime": "00:38:27"
        },
        {
            "source": "youtube",
            "title": "The Legend of 'Jeff'",
            "releaseDate": "2020-06-30",
            "links": [
                {
                    "link": "https://www.youtube.com/watch?v=9x2NaGkl6BI",
                    "availability": "Available",
                    "runtime": "00:18:04"
                }
            ],
            "aliases": [],
            "runtime": "00:18:04"
        },
        {
            "source": "youtube",
            "title": "There's Something About Casey...",
            "releaseDate": "2020-08-01",
            "links": [
                {
                    "link": "https://www.youtube.com/watch?v=eJt_afGN3IQ",
                    "availability": "Available",
                    "runtime": "01:07:54"
                }
            ],
            "aliases": [],
            "runtime": "01:07:54"
        },
        {
            "source": "youtube",
            "title": "Jennifer's Solution",
            "releaseDate": "2020-09-03",
            "links": [
                {
                    "link": "https://www.youtube.com/watch?v=UQt46gvYO40",
                    "availability": "Available",
                    "runtime": "01:31:00"
                }
            ],
            "aliases": [],
            "runtime": "01:31:00"
        },
        {
            "source": "youtube",
            "title": "Guilty until proven innocent.",
            "releaseDate": "2020-10-08",
            "links": [
                {
                    "link": "https://www.youtube.com/watch?v=BemHqUqcpI8",
                    "availability": "Available",
                    "runtime": "00:17:17"
                }
            ],
            "aliases": [],
            "runtime": "00:17:16"
        },
        {
            "source": "youtube",
            "title": "What pretending to be crazy looks like",
            "releaseDate": "2021-05-26",
            "links": [
                {
                    "link": "https://www.youtube.com/watch?v=Mwt35SEeR9w",
                    "availability": "Available",
                    "runtime": "00:59:05"
                }
            ],
            "aliases": [],
            "runtime": "00:59:04"
        },
        {
            "source": "youtube",
            "title": "The Interrogation Tape of Alek Minassian",
            "releaseDate": "2021-06-28",
            "links": [
                {
                    "link": "https://www.youtube.com/watch?v=z4Dck7J4Ks0",
                    "availability": "Available",
                    "runtime": "00:51:49"
                }
            ],
            "aliases": [],
            "runtime": "00:51:49"
        },
        {
            "source": "youtube",
            "title": "The Case of Brendt Christensen",
            "releaseDate": "2021-06-29",
            "links": [
                {
                    "link": "https://www.youtube.com/watch?v=rudSWhe_KD0",
                    "availability": "Available",
                    "runtime": "00:45:40"
                }
            ],
            "aliases": [],
            "runtime": "00:45:40"
        },
        {
            "source": "youtube",
            "title": "Christmas with Cliff",
            "releaseDate": "2021-12-20",
            "links": {},
            "aliases": [],
            "runtime": "00:32:56"
        },
        {
            "source": "youtube",
            "title": "Prince Andrew's guide to getting away with sex crimes",
            "releaseDate": "2022-02-15",
            "links": [
                {
                    "link": "https://www.youtube.com/watch?v=hi_ouCmuFTI",
                    "availability": "Available",
                    "runtime": "00:10:41"
                }
            ],
            "aliases": [],
            "runtime": "00:10:41"
        }
    ],
    "patreon": [
        {
            "source": "patreon",
            "title": "Adele Sorella, Elaine Campione, Nikolas Cruz, Russell Williams",
            "releaseDate": "2019-01-29",
            "link": "",
            "wistiaTitles": [],
            "patreonTitles": [],
            "runtime": "",
            "availability": "Unavailable"
        },
        {
            "source": "patreon",
            "title": "Stephanie Lazarus, Michael Rafferty, Dalia Dippolito",
            "releaseDate": "2019-01-29",
            "link": "",
            "wistiaTitles": [],
            "patreonTitles": [],
            "runtime": "",
            "availability": "Unavailable"
        },
        {
            "source": "patreon",
            "title": "Rachel Wade, Raymond Gates, Stephen McDaniel",
            "releaseDate": "2019-01-29",
            "link": "",
            "wistiaTitles": [],
            "patreonTitles": [],
            "runtime": "",
            "availability": "Unavailable"
        },
        {
            "source": "patreon",
            "title": "Juvenile Interrogation Analysis",
            "releaseDate": "2019-01-29",
            "link": "https://jimmyc.wistia.com/medias/3b074a75f235f11c5ae99062629628e2378804cdb9ddb70af9a30a60ec59a858",
            "wistiaTitles": [
                "Juvenile Interrogation Analysis"
            ],
            "patreonTitles": [
                "Juvenile Interrogations"
            ],
            "runtime": "00:58:13",
            "availability": "Available"
        },
        {
            "source": "patreon",
            "title": "Stephen Port, George Huguely",
            "releaseDate": "2019-01-29",
            "link": "",
            "wistiaTitles": [],
            "patreonTitles": [],
            "runtime": "",
            "availability": "Unavailable"
        },
        {
            "source": "patreon",
            "title": "The Case of Alek Minassian",
            "releaseDate": "2019-01-29",
            "link": "https://jimmyc.wistia.com/medias/9a9cc12c3d98fbc46ffe531ea63e3c72f7034c96768864903ff14175998e1849",
            "wistiaTitles": [
                "The Case of Alek Minassian"
            ],
            "patreonTitles": [
                "The Case of Alek Minassian"
            ],
            "runtime": "00:53:24",
            "availability": "Available"
        },
        {
            "source": "patreon",
            "title": "The Case of Chris Garnier",
            "releaseDate": "2019-02-09",
            "link": "https://jimmyc.wistia.com/medias/5c4f26d86656d636cac621a6fcc9914aacb63cf8b8259000c56fd1468f62305f",
            "wistiaTitles": [
                "The Case of Chris Garnier"
            ],
            "patreonTitles": [
                "The Case of Chris Garnier"
            ],
            "runtime": "00:31:02",
            "availability": "Available"
        },
        {
            "source": "patreon",
            "title": "The Lost Tapes - pt.2",
            "releaseDate": "2019-02-25",
            "link": "",
            "wistiaTitles": [],
            "patreonTitles": [],
            "runtime": "",
            "availability": "Unavailable"
        },
        {
            "source": "patreon",
            "title": "The 'Code'",
            "releaseDate": "2019-02-26",
            "link": "",
            "wistiaTitles": [],
            "patreonTitles": [],
            "runtime": "",
            "availability": "Unavailable"
        },
        {
            "source": "patreon",
            "title": "The Insanity Defense - pt. 2",
            "releaseDate": "2019-03-04",
            "link": "",
            "wistiaTitles": [],
            "patreonTitles": [],
            "runtime": "",
            "availability": "Unavailable"
        },
        {
            "source": "patreon",
            "title": "The Death Row Phenomenon",
            "releaseDate": "2019-03-04",
            "link": "https://jimmyc.wistia.com/medias/60027d16af1e94618a6b7348bf5b24202b6db7a497c45ceccc96b4bfc5a67011",
            "wistiaTitles": [
                "The Death Row Phenomenon"
            ],
            "patreonTitles": [
                "The Death Row Phenomenon"
            ],
            "runtime": "00:49:10",
            "availability": "Available"
        },
        {
            "source": "patreon",
            "title": "The Most Compelling Juvenile Interrogations - pt.1",
            "releaseDate": "2019-03-21",
            "link": "",
            "wistiaTitles": [],
            "patreonTitles": [],
            "runtime": "",
            "availability": "Unavailable"
        },
        {
            "source": "patreon",
            "title": "The Case of Chris Watts - Part 4",
            "releaseDate": "2019-03-21",
            "link": "https://jimmyc.wistia.com/medias/63e5bb6912f9f371c235bd7fcb4ae7df5756f70a5d5902d0c66dfcebbbfb36ec",
            "wistiaTitles": [
                "The Case of Chris Watts - Part 4"
            ],
            "patreonTitles": [
                "CWpt. 4"
            ],
            "runtime": "00:44:52",
            "availability": "Available"
        },
        {
            "source": "patreon",
            "title": "The 'Code' - parts 1 & 2",
            "releaseDate": "2019-03-21",
            "link": "",
            "wistiaTitles": [],
            "patreonTitles": [],
            "runtime": "",
            "availability": "Unavailable"
        },
        {
            "source": "patreon",
            "title": "Amber H and Cameron R",
            "releaseDate": "2019-03-21",
            "link": "https://jimmyc.wistia.com/medias/720f2525bbaca50cf18332ab6e29f8deba8d55e71c3844730abf3f203c2614da",
            "wistiaTitles": [
                "Amber H and Cameron R"
            ],
            "patreonTitles": [
                "Amber H and Cameron R"
            ],
            "runtime": "00:50:56",
            "availability": "Available"
        },
        {
            "source": "patreon",
            "title": "The Most Compelling Police Interrogations pt. 8",
            "releaseDate": "2019-03-31",
            "link": "",
            "wistiaTitles": [],
            "patreonTitles": [],
            "runtime": "",
            "availability": "Unavailable"
        },
        {
            "source": "patreon",
            "title": "The Interrogations of Mr. Matthews & Miss Hoare",
            "releaseDate": "2019-04-21",
            "link": "",
            "wistiaTitles": [],
            "patreonTitles": [],
            "runtime": "",
            "availability": "Unavailable"
        },
        {
            "source": "patreon",
            "title": "Online Predator Psychology",
            "releaseDate": "2019-05-01",
            "link": "https://jimmyc.wistia.com/medias/5f1401218d9dcc2bd568773a102e8d4188a5c7252126f24876bd2a73b13a0f0f",
            "wistiaTitles": [
                "Online Predator Psychology"
            ],
            "patreonTitles": [
                "The Psychology of Online Predators - Part 4",
                "The Psychology of Online Predators"
            ],
            "runtime": "00:30:24",
            "availability": "Available"
        },
        {
            "source": "patreon",
            "title": "Police Interrogation Analysis - 8 - 2",
            "releaseDate": "2019-05-31",
            "link": "https://jimmyc.wistia.com/medias/73bcc1af9c31a32edf0144deffad46e2f71e346a04fb71cc0a9d51d559a684be",
            "wistiaTitles": [
                "Police Interrogation Analysis - 8 - 2"
            ],
            "patreonTitles": [
                "Police Interrogations #Viewer Discretion Advised##"
            ],
            "runtime": "01:09:02",
            "availability": "Available"
        },
        {
            "source": "patreon",
            "title": "Police Interrogations pt. 8",
            "releaseDate": "2019-05-31",
            "link": "",
            "wistiaTitles": [],
            "patreonTitles": [],
            "runtime": "",
            "availability": "Unavailable"
        },
        {
            "source": "patreon",
            "title": "Police Interrogations pt. 9",
            "releaseDate": "2019-05-31",
            "link": "",
            "wistiaTitles": [],
            "patreonTitles": [],
            "runtime": "",
            "availability": "Unavailable"
        },
        {
            "source": "patreon",
            "title": "The Interrogation of Steven J. Williams",
            "releaseDate": "2019-06-19",
            "link": "https://jimmyc.wistia.com/medias/8b91a201bec67239aabbe979e14c86016301d8908895ce8e78bad8273a8e9f4e",
            "wistiaTitles": [
                "The Interrogation of Steven J. Williams"
            ],
            "patreonTitles": [
                "The Interrogation of Steven J. Williams"
            ],
            "runtime": "00:41:58",
            "availability": "Available"
        },
        {
            "source": "patreon",
            "title": "The Hidden Perspective - Part 1 - Invisible Enemy",
            "releaseDate": "2019-07-03",
            "link": "https://jimmyc.wistia.com/medias/112e9fb177bf21e94ea9f177196a4047d121ef14acc88eed3e087c76f59ec264",
            "wistiaTitles": [
                "The Hidden Perspective - Part 1 - Invisible Enemy"
            ],
            "patreonTitles": [
                "The Hidden Perspective - Part 1 - Invisible Enemy #Viewer Discretion Advised#"
            ],
            "runtime": "00:27:01",
            "availability": "Available"
        },
        {
            "source": "patreon",
            "title": "The Most Compelling Police Interrogations pt. 10",
            "releaseDate": "2019-07-03",
            "link": "",
            "wistiaTitles": [],
            "patreonTitles": [],
            "runtime": "",
            "availability": "Unavailable"
        },
        {
            "source": "patreon",
            "title": "The Psychology of Ted Bundy",
            "releaseDate": "2019-07-03",
            "link": "https://jimmyc.wistia.com/medias/1190dcf35887743053f3d521df3be6c490459072546adb046948fcab88054453",
            "wistiaTitles": [
                "The Psychology of Ted Bundy"
            ],
            "patreonTitles": [
                "The Psychology of Ted Bundy"
            ],
            "runtime": "00:50:56",
            "availability": "Available"
        },
        {
            "source": "patreon",
            "title": "Police Interrogations of The Online Predators",
            "releaseDate": "2019-07-17",
            "link": "https://jimmyc.wistia.com/medias/69f9cdd896c1b3523418a734462230b727c60e1b4d3ff22f1013f8b9ffd0f4b6",
            "wistiaTitles": [
                "Police Interrogations of The Online Predators"
            ],
            "patreonTitles": [
                "Police Interrogations of The Online Predators"
            ],
            "runtime": "00:49:15",
            "availability": "Available"
        },
        {
            "source": "patreon",
            "title": "Police Interrogations of The Online Predators",
            "releaseDate": "2019-07-17",
            "link": "",
            "wistiaTitles": [],
            "patreonTitles": [],
            "runtime": "",
            "availability": "Unavailable"
        },
        {
            "source": "patreon",
            "title": "Police Interrogations - 2",
            "releaseDate": "2019-07-31",
            "link": "https://jimmyc.wistia.com/medias/3f9cf58c43f49b681e6c69c64554836a2aa785a8cebff85da93c94b1ebff6c0e",
            "wistiaTitles": [
                "Police Interrogations - 2"
            ],
            "patreonTitles": [
                "Police Interrogations - 2"
            ],
            "runtime": "00:55:54",
            "availability": "Available"
        },
        {
            "source": "patreon",
            "title": "TMC Police Interrogations pt. 12",
            "releaseDate": "2019-08-14",
            "link": "https://jimmyc.wistia.com/medias/0a5f979bdcce35c1edda39cb7d9e8f6e4ef323cd28a8f74780e304fe26782639",
            "wistiaTitles": [
                "TMC Police Interrogations pt. 12"
            ],
            "patreonTitles": [
                "Police Interrogations - 3"
            ],
            "runtime": "01:03:09",
            "availability": "Available"
        },
        {
            "source": "patreon",
            "title": "TMC Police Interrogations pt. 13",
            "releaseDate": "2019-09-19",
            "link": "https://jimmyc.wistia.com/medias/dedafba8f8a673a63d46b8e2cb8b0444a0b744f5b57ef99177de6fbfa1017f36",
            "wistiaTitles": [
                "TMC Police Interrogations pt. 13"
            ],
            "patreonTitles": [
                "Police Interrogations - 4"
            ],
            "runtime": "01:05:50",
            "availability": "Available"
        },
        {
            "source": "patreon",
            "title": "The Hidden Perspective - pt. 2 - Roll of the Dice",
            "releaseDate": "2019-10-02",
            "link": "https://jimmyc.wistia.com/medias/5d078a5f19506fe068a3339e9e0436f927ca7c6e7869348a1f12185595edc305",
            "wistiaTitles": [
                "The Hidden Perspective - pt. 2 - Roll of the Dice"
            ],
            "patreonTitles": [
                "The Hidden Perspective - pt. 2 - Roll of the Dice #Viewer Discretion Advised#"
            ],
            "runtime": "00:23:53",
            "availability": "Available"
        },
        {
            "source": "patreon",
            "title": "TMC Police Interrogations pt. 14 #Viewer Discretion Advised#",
            "releaseDate": "2019-10-18",
            "link": "https://jimmyc.wistia.com/medias/51ab51b2e6e829bbcf633395a44837e2559925203115b9c52acfc15a1707166b",
            "wistiaTitles": [
                "TMC Police Interrogations pt. 14 #Viewer Discretion Advised#"
            ],
            "patreonTitles": [
                "Police Interrogations - 5 #Viewer Discretion Advised#"
            ],
            "runtime": "00:48:30",
            "availability": "Available"
        },
        {
            "source": "patreon",
            "title": "TMC Police Interrogations pt. 15 #Viewer Discretion Advised#",
            "releaseDate": "2019-11-05",
            "link": "https://jimmyc.wistia.com/medias/ad382d053a1cdc15d8b2640a447e57e23cc8aaec840d213e981de4386b899fdb",
            "wistiaTitles": [
                "TMC Police Interrogations pt. 15 #Viewer Discretion Advised#"
            ],
            "patreonTitles": [
                "Police Interrogations - 6 #Viewer Discretion Advised#"
            ],
            "runtime": "00:40:14",
            "availability": "Available"
        },
        {
            "source": "patreon",
            "title": "TMCPI pt.16 - Psychology of a Cop Killer.mp4",
            "releaseDate": "2019-11-29",
            "link": "https://jimmyc.wistia.com/medias/f5483bd7e41821d015687b84a86c8b4ace0beb1aadb19a6f652c82351af06118",
            "wistiaTitles": [
                "TMCPI pt.16 - Psychology of a Cop Killer.mp4"
            ],
            "patreonTitles": [
                "Police Interrogations - 7"
            ],
            "runtime": "00:55:41",
            "availability": "Available"
        },
        {
            "source": "patreon",
            "title": "Psychology of The 6th Floor",
            "releaseDate": "2019-12-30",
            "link": "https://jimmyc.wistia.com/medias/4ee15115abe7995e59d0652394ad57fc04b00b776c222bd585bec7bb9ec760d3",
            "wistiaTitles": [
                "Psychology of The 6th Floor"
            ],
            "patreonTitles": [
                "Psychology of The 6th Floor #Viewer Discretion Advised#"
            ],
            "runtime": "01:00:08",
            "availability": "Available"
        },
        {
            "source": "patreon",
            "title": "Chris Coleman, Levi Belfield, Brian David Mitchel.mp4",
            "releaseDate": "2020-01-30",
            "link": "https://jimmyc.wistia.com/medias/977fc0290bea23bb82cc3018dfa929a37fff35b86901a3c3b7c67c9e2c86be84",
            "wistiaTitles": [
                "Chris Coleman, Levi Belfield, Brian David Mitchel.mp4"
            ],
            "patreonTitles": [
                "Chris Coleman, Levi Belfield, Brian David Mitchel"
            ],
            "runtime": "00:29:27",
            "availability": "Available"
        },
        {
            "source": "patreon",
            "title": "The Interrogations of Mr. Mathews and Miss Hoare",
            "releaseDate": "2020-01-30",
            "link": "https://jimmyc.wistia.com/medias/4943aba1046f735ae917431afffed53b53dc543f88841ddd74801216a0d75d88",
            "wistiaTitles": [
                "The Interrogations of Mr. Mathews and Miss Hoare"
            ],
            "patreonTitles": [
                "The Interrogations of Mr. Mathews and Miss Hoare"
            ],
            "runtime": "00:53:51",
            "availability": "Available"
        },
        {
            "source": "patreon",
            "title": "Police Interrogation Analysis - 8 - 1",
            "releaseDate": "2020-01-30",
            "link": "https://jimmyc.wistia.com/medias/057126668b950610a9bef071bd74c933b5e048397813adf24f47387bf55ad174",
            "wistiaTitles": [
                "Police Interrogation Analysis - 8 - 1"
            ],
            "patreonTitles": [
                "Derek Saretzky, Cardinal George Pell, William Sandeson"
            ],
            "runtime": "00:50:14",
            "availability": "Available"
        },
        {
            "source": "patreon",
            "title": "The Case of Phoenix Sinclair",
            "releaseDate": "2020-01-30",
            "link": "https://jimmyc.wistia.com/medias/27de716b9a7681be5440c9791d8f10260153ef9a70edb3b0deb79b47c35a2c9a",
            "wistiaTitles": [
                "The Case of Phoenix Sinclair"
            ],
            "patreonTitles": [
                "Police Interrogations - 8 #Viewer Discretion Advised#"
            ],
            "runtime": "00:38:49",
            "availability": "Available"
        },
        {
            "source": "patreon",
            "title": "Police Interrogations pt.17",
            "releaseDate": "2020-01-30",
            "link": "",
            "wistiaTitles": [],
            "patreonTitles": [],
            "runtime": "",
            "availability": "Unavailable"
        },
        {
            "source": "patreon",
            "title": "The Case of Karina Vetrano",
            "releaseDate": "2020-01-30",
            "link": "https://jimmyc.wistia.com/medias/a1d230d34e4a8fce2544948ac072c6a02e9b6d0cc518349d97bcaa0c4f1f847b",
            "wistiaTitles": [
                "The Case of Karina Vetrano"
            ],
            "patreonTitles": [
                "The Case of Karina Vetrano"
            ],
            "runtime": "00:53:06",
            "availability": "Available"
        },
        {
            "source": "patreon",
            "title": "Police Interrogations pt. 7",
            "releaseDate": "2020-03-01",
            "link": "https://jimmyc.wistia.com/medias/3d6086125551e4bfb3208dfd5b19fadb08c7e7e2b3bc8409f2c7e9069f555972",
            "wistiaTitles": [
                "Police Interrogations pt. 7"
            ],
            "patreonTitles": [
                "Police Interrogations - 9",
                "The Most Compelling Police Interrogations pt. 7"
            ],
            "runtime": "01:03:24",
            "availability": "Available"
        },
        {
            "source": "patreon",
            "title": "The Interrogation of Jodi Arias - pt. 2",
            "releaseDate": "2020-03-16",
            "link": "https://jimmyc.wistia.com/medias/152010202709620a7f1eb2f1e394c4ad2a951de6bcf9edc180c2d255eb31c19f",
            "wistiaTitles": [
                "The Interrogation of Jodi Arias - pt. 2"
            ],
            "patreonTitles": [],
            "runtime": "01:09:40",
            "availability": "Available"
        },
        {
            "source": "patreon",
            "title": "Derek Medina, Special Operations Group, Jerome Ersland",
            "releaseDate": "2020-03-24",
            "link": "https://jimmyc.wistia.com/medias/5a50838560b4ec8567f9925151b3b37773c4651e42625f7a8d7c01fc6b465188",
            "wistiaTitles": [
                "Derek Medina, Special Operations Group, Jerome Ersland"
            ],
            "patreonTitles": [],
            "runtime": "00:37:02",
            "availability": "Available"
        },
        {
            "source": "patreon",
            "title": "The Most Compelling Police Interrogations pt. 9",
            "releaseDate": "2020-03-24",
            "link": "https://jimmyc.wistia.com/medias/4757e0b7a2f1062a756387e15e127b68e87b983db262c5bc192f9d3fec58e8c1",
            "wistiaTitles": [
                "The Most Compelling Police Interrogations pt. 9"
            ],
            "patreonTitles": [],
            "runtime": "01:21:36",
            "availability": "Available"
        },
        {
            "source": "patreon",
            "title": "Michael Dixon, Shayna Hubers, Thomas Chan",
            "releaseDate": "2020-03-24",
            "link": "https://jimmyc.wistia.com/medias/115531212b53f75e2752e5aae80d84295b655d13bfc554c78aa15fcc679e451a",
            "wistiaTitles": [
                "Michael Dixon, Shayna Hubers, Thomas Chan"
            ],
            "patreonTitles": [],
            "runtime": "",
            "availability": "Available"
        },
        {
            "source": "patreon",
            "title": "The Interrogation of George the 5th",
            "releaseDate": "2020-03-24",
            "link": "https://jimmyc.wistia.com/medias/0651d54bee655dba53d5526653dfa48697459c076935dfc4cc9b38c2386feb62",
            "wistiaTitles": [
                "The Interrogation of George the 5th"
            ],
            "patreonTitles": [],
            "runtime": "",
            "availability": "Available"
        },
        {
            "source": "patreon",
            "title": "TMC Police Interrogations pt. 11",
            "releaseDate": "2020-03-24",
            "link": "https://jimmyc.wistia.com/medias/3321b39f26cf27ae495649c469d9ac7960598a19963ba973fc8dd9f1d93494e3",
            "wistiaTitles": [
                "TMC Police Interrogations pt. 11"
            ],
            "patreonTitles": [],
            "runtime": "00:56:53",
            "availability": "Available"
        },
        {
            "source": "patreon",
            "title": "The Interrogation of Jodi Arias",
            "releaseDate": "2020-03-24",
            "link": "https://jimmyc.wistia.com/medias/d45f67cb461da68b0b0757ec2564778f0b4bee5f64dd289bc53e8eeea9c21193",
            "wistiaTitles": [
                "The Interrogation of Jodi Arias"
            ],
            "patreonTitles": [],
            "runtime": "00:46:35",
            "availability": "Available"
        },
        {
            "source": "patreon",
            "title": "The Case of Grant Amato",
            "releaseDate": "2020-03-24",
            "link": "https://jimmyc.wistia.com/medias/de573e5984fbf17c1a77cb78c8a3590406e79f7ea7e1473c4d79630dd6c99d74",
            "wistiaTitles": [
                "The Case of Grant Amato"
            ],
            "patreonTitles": [],
            "runtime": "",
            "availability": "Available"
        },
        {
            "source": "patreon",
            "title": "Police Interrogations",
            "releaseDate": "2020-03-24",
            "link": "https://jimmyc.wistia.com/medias/b291afdb421af50778e36a556d7aa276cffcd2b9700601b4e31d4d4d306e154a",
            "wistiaTitles": [
                "Police Interrogations"
            ],
            "patreonTitles": [],
            "runtime": "00:44:31",
            "availability": "Available"
        },
        {
            "source": "patreon",
            "title": "The Insanity Defense",
            "releaseDate": "2020-03-24",
            "link": "https://jimmyc.wistia.com/medias/587000d535ed0445673de8da87f4b3b71da3ad68cd2bd54e0d94736da24c5b76",
            "wistiaTitles": [
                "The Insanity Defense"
            ],
            "patreonTitles": [],
            "runtime": "01:02:06",
            "availability": "Available"
        },
        {
            "source": "patreon",
            "title": "The Case of Andy. B",
            "releaseDate": "2020-03-31",
            "link": "https://jimmyc.wistia.com/medias/12ba2b6b3d48f297b5d5d7f37a4a5d009867bb699c48c844c5cf2ba144707bb5",
            "wistiaTitles": [
                "The Case of Andy. B"
            ],
            "patreonTitles": [
                "The Case of Andy B. (extended) #Viewer Discretion Advised#"
            ],
            "runtime": "00:58:30",
            "availability": "Available"
        },
        {
            "source": "patreon",
            "title": "The Case of Mr. L",
            "releaseDate": "2020-04-04",
            "link": "https://jimmyc.wistia.com/medias/3059de305c0229d0a11329c816c25c027397ad56b3459712a0a42d0727e492f0",
            "wistiaTitles": [
                "The Case of Mr. L"
            ],
            "patreonTitles": [],
            "runtime": "",
            "availability": "Available"
        },
        {
            "source": "patreon",
            "title": "The Psychology of Miss. W",
            "releaseDate": "2020-05-31",
            "link": "https://jimmyc.wistia.com/medias/4dcee2e7837fd12ba0c105413989286f1e9c787bcbe0b9f37802a69c55ded857",
            "wistiaTitles": [
                "The Psychology of Miss. W"
            ],
            "patreonTitles": [
                "The Psychology of Miss. W #Viewer Discretion Advised#"
            ],
            "runtime": "01:23:47",
            "availability": "Available"
        }
    ]
}